eltime/__init__.py
eltime/__main__.py
eltime/info_dialog.py
eltime/sqlrecorder.py
eltime/texts.py
eltime-0.1.0.dist-info/entry_points.txt
eltime-0.1.0.dist-info/LICENSE
eltime-0.1.0.dist-info/WHEEL
eltime-0.1.0.dist-info/METADATA
eltime-0.1.0.dist-info/RECORD
